labmanager
test
suds
