Metadata-Version: 1.1
Name: labmanager
Version: 1.0.1
Summary: the labmanager cloud plugin for pagrant
Home-page: UNKNOWN
Author: UNKNOWN
Author-email: UNKNOWN
License: UNKNOWN
Keywords: framework testing
Platform: any
Classifier: Programming Language :: Python
